[{"text":null,"message_id":"?","context_id":"54a83226-82bd-390d-8dd1-57531179c622","post_id":"v-338950e1-cae3-359e-bfa3-af403b69d694_c-e9c103fc-85e6-3054-bb82-0c3f4a845ad0_a-54a83226-82bd-390d-8dd1-57531179c622","upvotes":"0","downvotes":"0","reports":"0","replies":"0","author_name":"Newsroom Bot","author_img":"https:\/\/s.yimg.com\/ge\/myc\/newsroom_app_icon_ios.png","author_guid":"1","score":0,"context_meta":{"post_id":"v-338950e1-cae3-359e-bfa3-af403b69d694_c-e9c103fc-85e6-3054-bb82-0c3f4a845ad0_a-54a83226-82bd-390d-8dd1-57531179c622","post_url":"https:\/\/www.yahoo.com\/newsroom\/vibes\/finance\/v-338950e1-cae3-359e-bfa3-af403b69d694_c-e9c103fc-85e6-3054-bb82-0c3f4a845ad0_a-54a83226-82bd-390d-8dd1-57531179c622","author":"ipostwhaticareabout","provider":"Yahoo Finance Video","provider_url":"https:\/\/finance.yahoo.com\/","provider_image":"","lead_attribution":"provider","link":"https:\/\/finance.yahoo.com\/video\/singapore-airlines-launch-worlds-longest-163046683.html","imgresolutions":[{"url":"https:\/\/s1.yimg.com\/uu\/api\/res\/1.2\/mN1IGmkriX_Lv0SEnw3paQ--\/YXBwaWQ9eXRhY2h5b247Zmk9c3RyaW07aD0zNjA7dz02NDA7\/https:\/\/slick-prod.s3-us-west-2.amazonaws.com\/slick_thumb\/giraffe-176414-1527697683673.jpg","height":360,"width":640,"tag":"fit-width-640"},{"url":"https:\/\/s1.yimg.com\/uu\/api\/res\/1.2\/FHsB_tdv6lbidZvfyBHvWA--\/YXBwaWQ9eXRhY2h5b247Zmk9c3RyaW07aD0xMjgwO3c9NzIwOw--\/https:\/\/slick-prod.s3-us-west-2.amazonaws.com\/slick_thumb\/giraffe-176414-1527697683673.jpg","height":1280,"width":720,"tag":"original"}],"img":"https:\/\/slick-prod.s3-us-west-2.amazonaws.com\/slick_thumb\/giraffe-176414-1527697683673.jpg","imgw":720,"imgh":1280,"title":"Singapore Airlines will launch the world's longest commercial flight in October","summary":null,"published_at":1527697959,"content_id":"54a83226-82bd-390d-8dd1-57531179c622","content_url":"https:\/\/finance.yahoo.com\/video\/singapore-airlines-launch-worlds-longest-163046683.html","content_published_at":1527697846,"content_time":1527697846,"content_relative_time":3,"reaction_count":0,"vibe_name":"Finance","vibe_id":"338950e1-cae3-359e-bfa3-af403b69d694","content_type":"video_link","aspect":0.560000000000000053290705182007513940334320068359375},"created_at":0,"comment_time":3,"comment_relative_time":3,"bot":true,"whitelisted_commenter":false},{"text":null,"message_id":"?","context_id":"a89df1bb-2c04-3449-a7b4-f4fc5c55e222","post_id":"v-338950e1-cae3-359e-bfa3-af403b69d694_c-974e8dd9-4ea7-3805-98ce-2b8faf3f956f_a-a89df1bb-2c04-3449-a7b4-f4fc5c55e222","upvotes":"0","downvotes":"0","reports":"0","replies":"0","author_name":"Newsroom Bot","author_img":"https:\/\/s.yimg.com\/ge\/myc\/newsroom_app_icon_ios.png","author_guid":"1","score":0,"context_meta":{"post_id":"v-338950e1-cae3-359e-bfa3-af403b69d694_c-974e8dd9-4ea7-3805-98ce-2b8faf3f956f_a-a89df1bb-2c04-3449-a7b4-f4fc5c55e222","post_url":"https:\/\/www.yahoo.com\/newsroom\/vibes\/finance\/alphabet-startup-heat-home-hole-5f4q66p","author":"ipostwhaticareabout","provider":"Bloomberg","provider_url":"http:\/\/www.bloomberg.com\/?cmpid=yhoo.logo","provider_image":"http:\/\/media.zenfs.com\/284\/2011\/06\/08\/bloomberg-106x27_102102.gif","lead_attribution":"provider","link":"https:\/\/www.bloomberg.com\/news\/articles\/2018-05-30\/alphabet-startup-will-heat-your-home-from-a-hole-in-the-ground?utm_source=yahoo&utm_medium=bd&utm_campaign=headline&cmpId=yhoo.headline&yptr=yahoo","imgresolutions":[{"url":"https:\/\/s1.yimg.com\/uu\/api\/res\/1.2\/k8n.Gre0jmHLQvXCS7dfbw--\/YXBwaWQ9eXRhY2h5b247Zmk9c3RyaW07aD0zNjA7dz02NDA7\/http:\/\/globalfinance.zenfs.com\/en_us\/News\/Reuters\/603c43c1bdf2f3ef639d67051ce86f30","height":360,"width":640,"tag":"fit-width-640"},{"url":"https:\/\/s1.yimg.com\/uu\/api\/res\/1.2\/GJtrlTuHwPQQDj.w9JyvcA--\/YXBwaWQ9eXRhY2h5b247Zmk9c3RyaW07aD04MDA7dz0xMjAwOw--\/http:\/\/globalfinance.zenfs.com\/en_us\/News\/Reuters\/603c43c1bdf2f3ef639d67051ce86f30","height":800,"width":1200,"tag":"original"}],"img":"http:\/\/globalfinance.zenfs.com\/en_us\/News\/Reuters\/603c43c1bdf2f3ef639d67051ce86f30","imgw":1200,"imgh":800,"title":"Alphabet Startup Heats Your Home From a Hole in the Ground","summary":"Dandelion Energy Inc., a company that emerged out of Alphabet Inc.\u2019s X incubator last year, says its custom-designed drilling rig and pump systems will help make geothermal heating more affordable to homeowners. The Brooklyn-based company expects to begin drilling wells in June for heating and cooling systems that will cost less than $20,000. Residential geothermal heating is uncommon, in part because the expense and effort to dig the wells make them costly to install in existing homes.","published_at":1527677417,"content_id":"a89df1bb-2c04-3449-a7b4-f4fc5c55e222","content_url":"https:\/\/www.bloomberg.com\/news\/articles\/2018-05-30\/alphabet-startup-will-heat-your-home-from-a-hole-in-the-ground?utm_source=yahoo&utm_medium=bd&utm_campaign=headline&cmpId=yhoo.headline&yptr=yahoo","content_published_at":1527674400,"content_time":1527674400,"content_relative_time":9,"reaction_count":0,"vibe_name":"Finance","vibe_id":"338950e1-cae3-359e-bfa3-af403b69d694","content_type":"link","aspect":null},"created_at":0,"comment_time":9,"comment_relative_time":9,"bot":true,"whitelisted_commenter":false},{"text":null,"message_id":"?","context_id":"94a9c99e-5c51-3801-88c2-f17006a8dacf","post_id":"v-338950e1-cae3-359e-bfa3-af403b69d694_c-74dc6e20-0bcc-35ba-ad5b-df60a4f5c15e_a-94a9c99e-5c51-3801-88c2-f17006a8dacf","upvotes":"0","downvotes":"0","reports":"0","replies":"0","author_name":"Newsroom Bot","author_img":"https:\/\/s.yimg.com\/ge\/myc\/newsroom_app_icon_ios.png","author_guid":"1","score":0,"context_meta":{"post_id":"v-338950e1-cae3-359e-bfa3-af403b69d694_c-74dc6e20-0bcc-35ba-ad5b-df60a4f5c15e_a-94a9c99e-5c51-3801-88c2-f17006a8dacf","post_url":"https:\/\/www.yahoo.com\/newsroom\/vibes\/finance\/v-338950e1-cae3-359e-bfa3-af403b69d694_c-74dc6e20-0bcc-35ba-ad5b-df60a4f5c15e_a-94a9c99e-5c51-3801-88c2-f17006a8dacf","author":"DeltaBravo","provider":"Yahoo Finance","provider_url":"http:\/\/finance.yahoo.com\/","provider_image":"https:\/\/media.zenfs.com\/creatr-images\/GLB\/2016-10-18\/b8a23750-94e1-11e6-86b6-b35ffeea45c2_finance.jpg","lead_attribution":"provider","link":"https:\/\/finance.yahoo.com\/news\/wednesday-morning-disappointing-u-s-economy-134825369.html","imgresolutions":[{"url":"https:\/\/s1.yimg.com\/uu\/api\/res\/1.2\/Oro28kIIXdF7ji7YCx75eQ--\/YXBwaWQ9eXRhY2h5b247Zmk9c3RyaW07aD0zNjA7dz02NDA7\/http:\/\/media.zenfs.com\/en\/homerun\/feed_manager_auto_publish_494\/5dc5eacd56b59b207f11e34914626963","height":360,"width":640,"tag":"fit-width-640"},{"url":"https:\/\/s1.yimg.com\/uu\/api\/res\/1.2\/qYnPauCplaLAOhK_yF68xA--\/YXBwaWQ9eXRhY2h5b247Zmk9c3RyaW07aD0zODQwO3c9NTc2MDs-\/http:\/\/media.zenfs.com\/en\/homerun\/feed_manager_auto_publish_494\/5dc5eacd56b59b207f11e34914626963","height":3840,"width":5760,"tag":"original"}],"img":"http:\/\/media.zenfs.com\/en\/homerun\/feed_manager_auto_publish_494\/5dc5eacd56b59b207f11e34914626963","imgw":5760,"imgh":3840,"title":"Wednesday morning was disappointing for the U.S. economy","summary":"Two key economic reports on the U.S. economy released Wednesday morning were disappointing relative to expectations. Yet the overall picture for the U.s. economy still remains pretty solid.","published_at":1527676229,"content_id":"94a9c99e-5c51-3801-88c2-f17006a8dacf","content_url":"https:\/\/finance.yahoo.com\/news\/wednesday-morning-disappointing-u-s-economy-134825369.html","content_published_at":1527688105,"content_time":1527688105,"content_relative_time":5,"reaction_count":0,"vibe_name":"Finance","vibe_id":"338950e1-cae3-359e-bfa3-af403b69d694","content_type":"link","aspect":null},"created_at":0,"comment_time":5,"comment_relative_time":5,"bot":true,"whitelisted_commenter":false},{"text":null,"message_id":"?","context_id":"ceeff806-0283-33e6-80a9-ef464e248f98","post_id":"v-338950e1-cae3-359e-bfa3-af403b69d694_c-63d2e4ae-f582-3176-8dda-9b80258f715c_a-ceeff806-0283-33e6-80a9-ef464e248f98","upvotes":"0","downvotes":"0","reports":"0","replies":"0","author_name":"Newsroom Bot","author_img":"https:\/\/s.yimg.com\/ge\/myc\/newsroom_app_icon_ios.png","author_guid":"1","score":0,"context_meta":{"post_id":"v-338950e1-cae3-359e-bfa3-af403b69d694_c-63d2e4ae-f582-3176-8dda-9b80258f715c_a-ceeff806-0283-33e6-80a9-ef464e248f98","post_url":"https:\/\/www.yahoo.com\/newsroom\/vibes\/finance\/tesla-opens-mysterious-payment-board-143jo2w","author":"third_watch","provider":"Bloomberg","provider_url":"http:\/\/www.bloomberg.com\/?cmpid=yhoo.logo","provider_image":"http:\/\/media.zenfs.com\/284\/2011\/06\/08\/bloomberg-106x27_102102.gif","lead_attribution":"provider","link":"https:\/\/finance.yahoo.com\/news\/tesla-opens-mysterious-payment-board-221714164.html","imgresolutions":[{"url":"https:\/\/s.yimg.com\/uu\/api\/res\/1.2\/QBA3ra9_OL.neMfm4ovN_Q--\/YXBwaWQ9eXRhY2h5b247Zmk9c3RyaW07aD0zNjA7dz02NDA7\/http:\/\/globalfinance.zenfs.com\/en_us\/News\/Reuters\/853fc18758a282b6753155c6cec2cc8a","height":360,"width":640,"tag":"fit-width-640"},{"url":"https:\/\/s.yimg.com\/uu\/api\/res\/1.2\/uEt0SEdSONw1fydXNZw3IA--\/YXBwaWQ9eXRhY2h5b247Zmk9c3RyaW07aD04MDA7dz0xMjAwOw--\/http:\/\/globalfinance.zenfs.com\/en_us\/News\/Reuters\/853fc18758a282b6753155c6cec2cc8a","height":800,"width":1200,"tag":"original"}],"img":"http:\/\/globalfinance.zenfs.com\/en_us\/News\/Reuters\/853fc18758a282b6753155c6cec2cc8a","imgw":1200,"imgh":800,"title":"Tesla Opens Up About Mysterious Payment to a Board Member's Firm","summary":"A private equity firm linked to a Tesla Inc. director spent more than 100 days at the carmaker\u2019s battery factory late last year to help increase Model 3 sedan production, according to a filing vouching for its beleaguered board. Valor Management Corp., whose founder and chief executive is Tesla\u2019s lead independent director Antonio Gracias, contributed to \u201cnumerous improvements that led to increased Model 3 production rates,\u201d Tesla said in the filing Tuesday. The carmaker said it paid Valor $34,347 to reimburse for travel, equipment and \u201cbudget lodging\u201d near the Nevada factory.","published_at":1527633313,"content_id":"ceeff806-0283-33e6-80a9-ef464e248f98","content_url":"https:\/\/finance.yahoo.com\/news\/tesla-opens-mysterious-payment-board-221714164.html","content_published_at":1527632234,"content_time":1527632234,"content_relative_time":21,"reaction_count":0,"vibe_name":"Finance","vibe_id":"338950e1-cae3-359e-bfa3-af403b69d694","content_type":"link","aspect":null},"created_at":0,"comment_time":21,"comment_relative_time":21,"bot":true,"whitelisted_commenter":false},{"text":null,"message_id":"?","context_id":"20104882-5788-3463-ba52-ca453f46e43a","post_id":"v-338950e1-cae3-359e-bfa3-af403b69d694_c-b56d7be0-7f1a-3ace-8292-2cc63b6723ff_a-20104882-5788-3463-ba52-ca453f46e43a","upvotes":"0","downvotes":"0","reports":"0","replies":"0","author_name":"Newsroom Bot","author_img":"https:\/\/s.yimg.com\/ge\/myc\/newsroom_app_icon_ios.png","author_guid":"1","score":0,"context_meta":{"post_id":"v-338950e1-cae3-359e-bfa3-af403b69d694_c-b56d7be0-7f1a-3ace-8292-2cc63b6723ff_a-20104882-5788-3463-ba52-ca453f46e43a","post_url":"https:\/\/www.yahoo.com\/newsroom\/vibes\/finance\/v-338950e1-cae3-359e-bfa3-af403b69d694_c-b56d7be0-7f1a-3ace-8292-2cc63b6723ff_a-20104882-5788-3463-ba52-ca453f46e43a","author":"nanook","provider":"Bloomberg","provider_url":"http:\/\/www.bloomberg.com\/?cmpid=yhoo.logo","provider_image":"http:\/\/media.zenfs.com\/284\/2011\/06\/08\/bloomberg-106x27_102102.gif","lead_attribution":"provider","link":"https:\/\/finance.yahoo.com\/news\/soros-sees-global-financial-crisis-085219344.html","imgresolutions":[{"url":"https:\/\/s1.yimg.com\/uu\/api\/res\/1.2\/PJ21ZRk6Qzv0svfCNz2qAA--\/YXBwaWQ9eXRhY2h5b247Zmk9c3RyaW07aD0zNjA7dz02NDA7\/http:\/\/globalfinance.zenfs.com\/en_us\/News\/Reuters\/836e52a7353af3f0bb8d5afa2d49d4e4","height":360,"width":640,"tag":"fit-width-640"},{"url":"https:\/\/s1.yimg.com\/uu\/api\/res\/1.2\/LBbU84ZFwQe9U6kfTPJ3iw--\/YXBwaWQ9eXRhY2h5b247Zmk9c3RyaW07aD04MDA7dz0xMjAwOw--\/http:\/\/globalfinance.zenfs.com\/en_us\/News\/Reuters\/836e52a7353af3f0bb8d5afa2d49d4e4","height":800,"width":1200,"tag":"original"}],"img":"http:\/\/globalfinance.zenfs.com\/en_us\/News\/Reuters\/836e52a7353af3f0bb8d5afa2d49d4e4","imgw":1200,"imgh":800,"title":"Soros Sees New Global Financial Crisis Brewing, EU Under Threat","summary":"A surging dollar and a capital flight from emerging markets may lead to another \u201cmajor\u201d financial crisis, investor George Soros said, warning the European Union that it\u2019s facing an imminent existential threat. The \u201ctermination\u201d of the nuclear deal with Iran and the \u201cdestruction\u201d of the transatlantic alliance between the EU and the U.S. are \u201cbound to have a negative effect on the European economy and cause other dislocations,\u201d including a devaluing of emerging-market currencies, Soros said in a speech in Paris on Tuesday. The stark warning from the billionaire money manager comes as Italian bond yields have jumped to multi-year highs and major emerging economies including Turkey and Argentina are struggling to contain the fallout from runaway inflation.","published_at":1527625523,"content_id":"20104882-5788-3463-ba52-ca453f46e43a","content_url":"https:\/\/finance.yahoo.com\/news\/soros-sees-global-financial-crisis-085219344.html","content_published_at":1527583939,"content_time":1527583939,"content_relative_time":34,"reaction_count":0,"vibe_name":"Finance","vibe_id":"338950e1-cae3-359e-bfa3-af403b69d694","content_type":"link","aspect":null},"created_at":0,"comment_time":34,"comment_relative_time":34,"bot":true,"whitelisted_commenter":false},{"text":null,"message_id":"?","context_id":"49bd8056-ec9c-33d2-96b9-a5802b96b875","post_id":"v-338950e1-cae3-359e-bfa3-af403b69d694_c-13f684e2-faca-3e0a-8b33-c1de275dc4ec_a-49bd8056-ec9c-33d2-96b9-a5802b96b875","upvotes":"0","downvotes":"0","reports":"0","replies":"0","author_name":"Newsroom Bot","author_img":"https:\/\/s.yimg.com\/ge\/myc\/newsroom_app_icon_ios.png","author_guid":"1","score":0,"context_meta":{"post_id":"v-338950e1-cae3-359e-bfa3-af403b69d694_c-13f684e2-faca-3e0a-8b33-c1de275dc4ec_a-49bd8056-ec9c-33d2-96b9-a5802b96b875","post_url":"https:\/\/www.yahoo.com\/newsroom\/vibes\/finance\/v-338950e1-cae3-359e-bfa3-af403b69d694_c-13f684e2-faca-3e0a-8b33-c1de275dc4ec_a-49bd8056-ec9c-33d2-96b9-a5802b96b875","author":"rocky.j.mountain","provider":"TechCrunch","provider_url":"https:\/\/techcrunch.com\/","provider_image":"https:\/\/s.yimg.com\/os\/creatr-images\/GLB\/2017-05-23\/e43c7660-3ff3-11e7-9fa9-c994bde64e92_techcrunch.svg","lead_attribution":"provider","link":"https:\/\/finance.yahoo.com\/video\/acorns-hits-3-5-million-194547113.html","imgresolutions":[{"url":"https:\/\/s.yimg.com\/uu\/api\/res\/1.2\/PrloVMbLTurRjt0ZrIZvDg--\/YXBwaWQ9eXRhY2h5b247Zmk9c3RyaW07aD0zNjA7dz02NDA7\/https:\/\/slick-prod.s3-us-west-2.amazonaws.com\/slick_thumb\/giraffe-176048-1527623025414.jpg","height":360,"width":640,"tag":"fit-width-640"},{"url":"https:\/\/s.yimg.com\/uu\/api\/res\/1.2\/zmqeZhzWexZ1bfrO36KGgA--\/YXBwaWQ9eXRhY2h5b247Zmk9c3RyaW07aD0xMjgwO3c9NzIwOw--\/https:\/\/slick-prod.s3-us-west-2.amazonaws.com\/slick_thumb\/giraffe-176048-1527623025414.jpg","height":1280,"width":720,"tag":"original"}],"img":"https:\/\/slick-prod.s3-us-west-2.amazonaws.com\/slick_thumb\/giraffe-176048-1527623025414.jpg","imgw":720,"imgh":1280,"title":"Acorns hits 3.5 million users, sees 100,000 sign-ups for retirement product","summary":null,"published_at":1527623372,"content_id":"49bd8056-ec9c-33d2-96b9-a5802b96b875","content_url":"https:\/\/finance.yahoo.com\/video\/acorns-hits-3-5-million-194547113.html","content_published_at":1527623147,"content_time":1527623147,"content_relative_time":23,"reaction_count":0,"vibe_name":"Finance","vibe_id":"338950e1-cae3-359e-bfa3-af403b69d694","content_type":"video_link","aspect":0.560000000000000053290705182007513940334320068359375},"created_at":0,"comment_time":23,"comment_relative_time":23,"bot":true,"whitelisted_commenter":false},{"text":null,"message_id":"?","context_id":"59c641c5-f196-3bcf-a66b-2ea41f4b0b86","post_id":"v-338950e1-cae3-359e-bfa3-af403b69d694_c-7b93ba62-97ae-3187-806b-1d82cd3a78ab_a-59c641c5-f196-3bcf-a66b-2ea41f4b0b86","upvotes":"0","downvotes":"0","reports":"0","replies":"0","author_name":"Newsroom Bot","author_img":"https:\/\/s.yimg.com\/ge\/myc\/newsroom_app_icon_ios.png","author_guid":"1","score":0,"context_meta":{"post_id":"v-338950e1-cae3-359e-bfa3-af403b69d694_c-7b93ba62-97ae-3187-806b-1d82cd3a78ab_a-59c641c5-f196-3bcf-a66b-2ea41f4b0b86","post_url":"https:\/\/www.yahoo.com\/newsroom\/vibes\/finance\/more-bad-news-freds-removed-1n5acgm","author":"ipostwhaticareabout","provider":"TheStreet.com","provider_url":"http:\/\/www.thestreet.com\/","provider_image":"http:\/\/media.zenfs.com\/284\/2011\/06\/08\/thestreet-106x27_153053.gif","lead_attribution":"provider","link":"https:\/\/www.thestreet.com\/markets\/bad-news-for-freds-after-it-is-removed-from-small-caps-index-14603944?puc=yahoo&cm_ven=YAHOO&yptr=yahoo","imgresolutions":null,"img":null,"imgw":null,"imgh":null,"title":"More Bad News for Fred's After It's Removed From S&P SmallCap 600 Index","summary":"Fred's Inc. is still suffering. On Friday, May 25, the S&P Dow Jones Indices announced changes to the S&P SmallCap 600. Fred's will be replaced by GameStop Corp. . The announcement comes after Fred's lost three boardmembers on Friday.","published_at":1527614424,"content_id":"59c641c5-f196-3bcf-a66b-2ea41f4b0b86","content_url":"https:\/\/www.thestreet.com\/markets\/bad-news-for-freds-after-it-is-removed-from-small-caps-index-14603944?puc=yahoo&cm_ven=YAHOO&yptr=yahoo","content_published_at":1527614280,"content_time":1527614280,"content_relative_time":26,"reaction_count":0,"vibe_name":"Finance","vibe_id":"338950e1-cae3-359e-bfa3-af403b69d694","content_type":"link","aspect":null},"created_at":0,"comment_time":26,"comment_relative_time":26,"bot":true,"whitelisted_commenter":false},{"text":null,"message_id":"?","context_id":"cd84d052-09ed-3230-96f4-cb7fee7b65a7","post_id":"v-338950e1-cae3-359e-bfa3-af403b69d694_c-279e1820-c4db-34d0-b1c4-2627bb2014f2_a-cd84d052-09ed-3230-96f4-cb7fee7b65a7","upvotes":"0","downvotes":"0","reports":"0","replies":"0","author_name":"Newsroom Bot","author_img":"https:\/\/s.yimg.com\/ge\/myc\/newsroom_app_icon_ios.png","author_guid":"1","score":0,"context_meta":{"post_id":"v-338950e1-cae3-359e-bfa3-af403b69d694_c-279e1820-c4db-34d0-b1c4-2627bb2014f2_a-cd84d052-09ed-3230-96f4-cb7fee7b65a7","post_url":"https:\/\/www.yahoo.com\/newsroom\/vibes\/finance\/v-338950e1-cae3-359e-bfa3-af403b69d694_c-279e1820-c4db-34d0-b1c4-2627bb2014f2_a-cd84d052-09ed-3230-96f4-cb7fee7b65a7","author":"captainunderoos","provider":"Market Realist","provider_url":"http:\/\/marketrealist.com","provider_image":"http:\/\/l.yimg.com\/os\/284\/2013\/07\/08\/MR-green-sml-png_192450.png","lead_attribution":"provider","link":"http:\/\/marketrealist.com\/2018\/05\/why-oils-rally-is-cooling\/?utm_source=yahoo&utm_medium=feed&yptr=yahoo","imgresolutions":[{"url":"https:\/\/s1.yimg.com\/uu\/api\/res\/1.2\/SqhCSZ3i5g2Qf.jNA2T9HA--\/YXBwaWQ9eXRhY2h5b247Zmk9c3RyaW07aD0zNjA7dz02NDA7\/http:\/\/media.zenfs.com\/en-US\/homerun\/marketrealist.com\/5fe6d5943ba04c47685a3222d2897210","height":360,"width":640,"tag":"fit-width-640"},{"url":"https:\/\/s1.yimg.com\/uu\/api\/res\/1.2\/EIQYN2eRPQyzhe6w0Z3j9w--\/YXBwaWQ9eXRhY2h5b247Zmk9c3RyaW07aD0yMDA7dz0zMDA7\/http:\/\/media.zenfs.com\/en-US\/homerun\/marketrealist.com\/5fe6d5943ba04c47685a3222d2897210","height":200,"width":300,"tag":"original"}],"img":"http:\/\/media.zenfs.com\/en-US\/homerun\/marketrealist.com\/5fe6d5943ba04c47685a3222d2897210","imgw":300,"imgh":200,"title":"Why Oil\u2019s Rally Is Cooling","summary":"Between May 18 and May 25, US crude oil July futures fell 4.9%\u2014the steepest weekly decline since February 9. On May 25, US crude oil July futures settled at $67.88 per barrel\u2014their first time below the $70.00 level since May 8.","published_at":1527614294,"content_id":"cd84d052-09ed-3230-96f4-cb7fee7b65a7","content_url":"http:\/\/marketrealist.com\/2018\/05\/why-oils-rally-is-cooling\/?utm_source=yahoo&utm_medium=feed&yptr=yahoo","content_published_at":1527609653,"content_time":1527609653,"content_relative_time":27,"reaction_count":0,"vibe_name":"Finance","vibe_id":"338950e1-cae3-359e-bfa3-af403b69d694","content_type":"link","aspect":null},"created_at":0,"comment_time":27,"comment_relative_time":27,"bot":true,"whitelisted_commenter":false},{"text":null,"message_id":"?","context_id":"dbf81ab4-ce1f-3095-b469-1e82761fa6bb","post_id":"v-338950e1-cae3-359e-bfa3-af403b69d694_c-7dccd765-577c-37ab-bebb-83dfbb54fa05_a-dbf81ab4-ce1f-3095-b469-1e82761fa6bb","upvotes":"0","downvotes":"0","reports":"0","replies":"0","author_name":"Newsroom Bot","author_img":"https:\/\/s.yimg.com\/ge\/myc\/newsroom_app_icon_ios.png","author_guid":"1","score":0,"context_meta":{"post_id":"v-338950e1-cae3-359e-bfa3-af403b69d694_c-7dccd765-577c-37ab-bebb-83dfbb54fa05_a-dbf81ab4-ce1f-3095-b469-1e82761fa6bb","post_url":"https:\/\/www.yahoo.com\/newsroom\/vibes\/finance\/v-338950e1-cae3-359e-bfa3-af403b69d694_c-7dccd765-577c-37ab-bebb-83dfbb54fa05_a-dbf81ab4-ce1f-3095-b469-1e82761fa6bb","author":"third_watch","provider":"Motley Fool","provider_url":"http:\/\/www.fool.com\/","provider_image":"https:\/\/s.yimg.com\/os\/creatr-images\/GLB\/2017-10-10\/7992db30-ae00-11e7-987d-519fbcf9902a_MotleyFool2.png","lead_attribution":"provider","link":"https:\/\/finance.yahoo.com\/news\/why-universal-display-windstream-holdings-203100367.html","imgresolutions":[{"url":"https:\/\/s1.yimg.com\/uu\/api\/res\/1.2\/yWqjKNNaP_O7kY9CH6sVEg--\/YXBwaWQ9eXRhY2h5b247Zmk9c3RyaW07aD0zNjA7dz02NDA7\/http:\/\/media.zenfs.com\/en-US\/homerun\/motleyfool.com\/3760c042b9e314363cde5259c62e7f3f","height":360,"width":640,"tag":"fit-width-640"},{"url":"https:\/\/s1.yimg.com\/uu\/api\/res\/1.2\/0_wX7JcJ7YL4I1GXb0M3Gg--\/YXBwaWQ9eXRhY2h5b247Zmk9c3RyaW07aD0yMTk7dz01ODA7\/http:\/\/media.zenfs.com\/en-US\/homerun\/motleyfool.com\/3760c042b9e314363cde5259c62e7f3f","height":219,"width":580,"tag":"original"}],"img":"http:\/\/media.zenfs.com\/en-US\/homerun\/motleyfool.com\/3760c042b9e314363cde5259c62e7f3f","imgw":580,"imgh":219,"title":"Why Universal Display, Windstream Holdings, and American Woodmark Jumped Today","summary":"Find out which of these stocks got a nice boost from a major mobile device maker.","published_at":1527600249,"content_id":"dbf81ab4-ce1f-3095-b469-1e82761fa6bb","content_url":"https:\/\/finance.yahoo.com\/news\/why-universal-display-windstream-holdings-203100367.html","content_published_at":1527625860,"content_time":1527625860,"content_relative_time":22,"reaction_count":0,"vibe_name":"Finance","vibe_id":"338950e1-cae3-359e-bfa3-af403b69d694","content_type":"link","aspect":null},"created_at":0,"comment_time":22,"comment_relative_time":22,"bot":true,"whitelisted_commenter":false},{"text":null,"message_id":"?","context_id":"466fccb6-d1ae-344d-99a1-d5fff3f25430","post_id":"v-338950e1-cae3-359e-bfa3-af403b69d694_c-d09343eb-6037-32ca-b973-4df14863bae3_a-466fccb6-d1ae-344d-99a1-d5fff3f25430","upvotes":"0","downvotes":"0","reports":"0","replies":"0","author_name":"Newsroom Bot","author_img":"https:\/\/s.yimg.com\/ge\/myc\/newsroom_app_icon_ios.png","author_guid":"1","score":0,"context_meta":{"post_id":"v-338950e1-cae3-359e-bfa3-af403b69d694_c-d09343eb-6037-32ca-b973-4df14863bae3_a-466fccb6-d1ae-344d-99a1-d5fff3f25430","post_url":"https:\/\/www.yahoo.com\/newsroom\/vibes\/finance\/leucadia-national-luk-renamed-jefferies-2jzjf18","author":"DeltaBravo","provider":"Zacks","provider_url":"http:\/\/www.zacks.com\/","provider_image":"http:\/\/media.zenfs.com\/284\/2011\/06\/08\/zacks1-106x27_152730.gif","lead_attribution":"provider","link":"https:\/\/finance.yahoo.com\/news\/leucadia-national-luk-renamed-jefferies-151203248.html","imgresolutions":[{"url":"https:\/\/s1.yimg.com\/uu\/api\/res\/1.2\/39FavRFsnIq94aBvT8iIFQ--\/YXBwaWQ9eXRhY2h5b247Zmk9c3RyaW07aD0zNjA7dz02NDA7\/http:\/\/media.zenfs.com\/en-US\/homerun\/zacks.com\/3496571a811465d910e99bd171c71a94","height":360,"width":640,"tag":"fit-width-640"},{"url":"https:\/\/s1.yimg.com\/uu\/api\/res\/1.2\/USG2NqLov6.ZoFa8AaRjHA--\/YXBwaWQ9eXRhY2h5b247Zmk9c3RyaW07aD02NzY7dz02MzU7\/http:\/\/media.zenfs.com\/en-US\/homerun\/zacks.com\/3496571a811465d910e99bd171c71a94","height":676,"width":635,"tag":"original"}],"img":"http:\/\/media.zenfs.com\/en-US\/homerun\/zacks.com\/3496571a811465d910e99bd171c71a94","imgw":635,"imgh":676,"title":"Leucadia National (LUK) Renamed as Jefferies Financial Group","summary":"Leucadia National (LUK) renames itself as Jefferies Financial Group after receiving a green signal from its shareholders.","published_at":1527599420,"content_id":"466fccb6-d1ae-344d-99a1-d5fff3f25430","content_url":"https:\/\/finance.yahoo.com\/news\/leucadia-national-luk-renamed-jefferies-151203248.html","content_published_at":1527174723,"content_time":1527174723,"content_relative_time":148,"reaction_count":0,"vibe_name":"Finance","vibe_id":"338950e1-cae3-359e-bfa3-af403b69d694","content_type":"link","aspect":null},"created_at":0,"comment_time":148,"comment_relative_time":148,"bot":true,"whitelisted_commenter":false},{"text":null,"message_id":"?","context_id":"72460b37-cf66-39b9-be28-8f43ce45355d","post_id":"v-338950e1-cae3-359e-bfa3-af403b69d694_c-e0ae9154-8d01-3469-bfc9-4656444283f1_a-72460b37-cf66-39b9-be28-8f43ce45355d","upvotes":"0","downvotes":"0","reports":"0","replies":"0","author_name":"Newsroom Bot","author_img":"https:\/\/s.yimg.com\/ge\/myc\/newsroom_app_icon_ios.png","author_guid":"1","score":0,"context_meta":{"post_id":"v-338950e1-cae3-359e-bfa3-af403b69d694_c-e0ae9154-8d01-3469-bfc9-4656444283f1_a-72460b37-cf66-39b9-be28-8f43ce45355d","post_url":"https:\/\/www.yahoo.com\/newsroom\/vibes\/finance\/v-338950e1-cae3-359e-bfa3-af403b69d694_c-e0ae9154-8d01-3469-bfc9-4656444283f1_a-72460b37-cf66-39b9-be28-8f43ce45355d","author":"third_watch","provider":"Yahoo Finance Video","provider_url":"https:\/\/finance.yahoo.com\/","provider_image":"","lead_attribution":"provider","link":"https:\/\/finance.yahoo.com\/video\/american-housing-market-inventory-problem-122113354.html","imgresolutions":[{"url":"https:\/\/s.yimg.com\/uu\/api\/res\/1.2\/yljMJESS1ImJTXTlDEfCvA--\/YXBwaWQ9eXRhY2h5b247Zmk9c3RyaW07aD0zNjA7dz02NDA7\/https:\/\/slick-prod.s3-us-west-2.amazonaws.com\/slick_thumb\/giraffe-175751-1527596135543.jpg","height":360,"width":640,"tag":"fit-width-640"},{"url":"https:\/\/s.yimg.com\/uu\/api\/res\/1.2\/NAe8Cn4nAH5k4XzafnOSMw--\/YXBwaWQ9eXRhY2h5b247Zmk9c3RyaW07aD0xMjgwO3c9NzIwOw--\/https:\/\/slick-prod.s3-us-west-2.amazonaws.com\/slick_thumb\/giraffe-175751-1527596135543.jpg","height":1280,"width":720,"tag":"original"}],"img":"https:\/\/slick-prod.s3-us-west-2.amazonaws.com\/slick_thumb\/giraffe-175751-1527596135543.jpg","imgw":720,"imgh":1280,"title":"The American housing market has an inventory problem","summary":null,"published_at":1527596769,"content_id":"72460b37-cf66-39b9-be28-8f43ce45355d","content_url":"https:\/\/finance.yahoo.com\/video\/american-housing-market-inventory-problem-122113354.html","content_published_at":1527596473,"content_time":1527596473,"content_relative_time":31,"reaction_count":0,"vibe_name":"Finance","vibe_id":"338950e1-cae3-359e-bfa3-af403b69d694","content_type":"video_link","aspect":0.560000000000000053290705182007513940334320068359375},"created_at":0,"comment_time":31,"comment_relative_time":31,"bot":true,"whitelisted_commenter":false},{"text":null,"message_id":"?","context_id":"14b0888e-0361-3aed-83e5-8d0abf8d2a77","post_id":"v-338950e1-cae3-359e-bfa3-af403b69d694_c-a149408d-f1e3-3659-8acf-3906dda88476_a-14b0888e-0361-3aed-83e5-8d0abf8d2a77","upvotes":"0","downvotes":"0","reports":"0","replies":"0","author_name":"Newsroom Bot","author_img":"https:\/\/s.yimg.com\/ge\/myc\/newsroom_app_icon_ios.png","author_guid":"1","score":0,"context_meta":{"post_id":"v-338950e1-cae3-359e-bfa3-af403b69d694_c-a149408d-f1e3-3659-8acf-3906dda88476_a-14b0888e-0361-3aed-83e5-8d0abf8d2a77","post_url":"https:\/\/www.yahoo.com\/newsroom\/vibes\/finance\/v-338950e1-cae3-359e-bfa3-af403b69d694_c-a149408d-f1e3-3659-8acf-3906dda88476_a-14b0888e-0361-3aed-83e5-8d0abf8d2a77","author":"ipostwhaticareabout","provider":"Reuters","provider_url":"http:\/\/www.reuters.com\/","provider_image":"http:\/\/media.zenfs.com\/284\/2011\/06\/21\/reuters-85x27_113626.gif","lead_attribution":"provider","link":"https:\/\/finance.yahoo.com\/news\/canada-buy-kinder-morgans-trans-132151097.html","imgresolutions":[{"url":"https:\/\/s1.yimg.com\/uu\/api\/res\/1.2\/Sw5QT2KFTt5fnbyCoVZiNA--\/YXBwaWQ9eXRhY2h5b247Zmk9c3RyaW07aD0zNjA7dz02NDA7\/http:\/\/globalfinance.zenfs.com\/images\/US_AHTTP_REUTERS_OLUSBUS_WRAPPER_H_LIVE_NEW\/2018-05-29T193947Z_1_LYNXNPEE4S1SA_RTROPTP_3_KINDER-MORGAN-CN-PIPELINE_original.jpg","height":360,"width":640,"tag":"fit-width-640"},{"url":"https:\/\/s1.yimg.com\/uu\/api\/res\/1.2\/cZfN5OfWOTO77X_xQxydzQ--\/YXBwaWQ9eXRhY2h5b247Zmk9c3RyaW07aD00OTA7dz04MDA7\/http:\/\/globalfinance.zenfs.com\/images\/US_AHTTP_REUTERS_OLUSBUS_WRAPPER_H_LIVE_NEW\/2018-05-29T193947Z_1_LYNXNPEE4S1SA_RTROPTP_3_KINDER-MORGAN-CN-PIPELINE_original.jpg","height":490,"width":800,"tag":"original"}],"img":"http:\/\/globalfinance.zenfs.com\/images\/US_AHTTP_REUTERS_OLUSBUS_WRAPPER_H_LIVE_NEW\/2018-05-29T193947Z_1_LYNXNPEE4S1SA_RTROPTP_3_KINDER-MORGAN-CN-PIPELINE_original.jpg","imgw":800,"imgh":490,"title":"Canada to buy Kinder Morgan oil pipeline in bid to save project","summary":"OTTAWA\/WINNIPEG (Reuters) - Canada will buy Kinder Morgan Canada Ltd's (KML.TO) Trans Mountain pipeline for C$4.5 billion ($3.5 billion), the government said on Tuesday, hoping to save a project that faces formidable political and environmental opposition. Finance Minister Bill Morneau said purchasing the pipeline was the only way to ensure that a planned expansion could proceed. The pipeline, running from the oil sands of Alberta to a port in the Pacific province of British Columbia, would allow Canadian crude to gain greater access to foreign markets and higher prices.","published_at":1527596002,"content_id":"14b0888e-0361-3aed-83e5-8d0abf8d2a77","content_url":"https:\/\/finance.yahoo.com\/news\/canada-buy-kinder-morgans-trans-132151097.html","content_published_at":1527631211,"content_time":1527631211,"content_relative_time":21,"reaction_count":1,"vibe_name":"Finance","vibe_id":"338950e1-cae3-359e-bfa3-af403b69d694","content_type":"link","aspect":null},"created_at":0,"comment_time":21,"comment_relative_time":21,"bot":true,"whitelisted_commenter":false}]